mlshortcuts/__init__.py
mlshortcuts/main.py
mlshortcuts-0.1.1.dist-info/METADATA
mlshortcuts-0.1.1.dist-info/WHEEL
mlshortcuts-0.1.1.dist-info/entry_points.txt
mlshortcuts-0.1.1.dist-info/top_level.txt
mlshortcuts-0.1.1.dist-info/RECORD
